{
  "indexes": [
    {
      "collectionGroup": "scans",
      "fields": [
        {
          "fieldPath": "doctorId",
          "order": "ASCENDING"
        },
        {
          "fieldPath": "completedAt",
          "order": "DESCENDING"
        }
      ]
    },
    {
      "collectionGroup": "scans",
      "fields": [
        {
          "fieldPath": "patientId",
          "order": "ASCENDING"
        },
        {
          "fieldPath": "completedAt",
          "order": "DESCENDING"
        }
      ]
    },
    {
      "collectionGroup": "patients",
      "fields": [
        {
          "fieldPath": "doctorId",
          "order": "ASCENDING"
        },
        {
          "fieldPath": "createdAt",
          "order": "DESCENDING"
        }
      ]
    }
  ]
}
